[
  {
    "id": 1,
    "asset_id": 64,
    "user_id": 3,
    "inspector_name": "신재훈",
    "user_team": "자동화팀",
    "asset_code": "A16485",
    "asset_type": "태블릿",
    "asset_info": {
      "model_name": "Omron Elite 500",
      "usage": "개인",
      "serial_number": "SN-655780486"
    },
    "inspection_count": 1,
    "inspection_date": "2025-05-21T23:26:57.526Z",
    "department_confirm": "품질관리실",
    "is_verified": true
  },
  {
    "id": 2,
    "asset_id": 8,
    "user_id": 3,
    "inspector_name": null,
    "user_team": null,
    "asset_code": "A05631",
    "asset_type": "노트북",
    "asset_info": {
      "model_name": null,
      "usage": "개인",
      "serial_number": null
    },
    "inspection_count": 1,
    "inspection_date": "2025-08-13T07:08:12.745Z",
    "department_confirm": null,
    "is_verified": false
  },
  {
    "id": 3,
    "asset_id": 50,
    "user_id": 1,
    "inspector_name": null,
    "user_team": null,
    "asset_code": "A40973",
    "asset_type": "노트북",
    "asset_info": {
      "model_name": null,
      "usage": "개인",
      "serial_number": null
    },
    "inspection_count": 1,
    "inspection_date": "2025-08-28T09:12:38.389Z",
    "department_confirm": null,
    "is_verified": false
  },
  {
    "id": 4,
    "asset_id": 70,
    "user_id": 2,
    "inspector_name": null,
    "user_team": null,
    "asset_code": "A62988",
    "asset_type": "태블릿",
    "asset_info": {
      "model_name": null,
      "usage": "개인",
      "serial_number": null
    },
    "inspection_count": 1,
    "inspection_date": "2025-06-15T23:29:50.136Z",
    "department_confirm": null,
    "is_verified": false
  },
  {
    "id": 5,
    "asset_id": 42,
    "user_id": 2,
    "inspector_name": "정가빈",
    "user_team": "콘텐츠팀",
    "asset_code": "A13167",
    "asset_type": "소모품",
    "asset_info": {
      "model_name": "HP Prime M2",
      "usage": "개인",
      "serial_number": "SN-710405835"
    },
    "inspection_count": 1,
    "inspection_date": "2025-06-11T03:46:59.648Z",
    "department_confirm": "R&D실",
    "is_verified": true
  },
  {
    "id": 6,
    "asset_id": 26,
    "user_id": 3,
    "inspector_name": null,
    "user_team": null,
    "asset_code": "A79434",
    "asset_type": "소모품",
    "asset_info": {
      "model_name": null,
      "usage": "개인",
      "serial_number": null
    },
    "inspection_count": 1,
    "inspection_date": "2025-07-27T02:39:37.041Z",
    "department_confirm": null,
    "is_verified": false
  },
  {
    "id": 7,
    "asset_id": 7,
    "user_id": 1,
    "inspector_name": "신지용",
    "user_team": "자동화팀",
    "asset_code": "A27969",
    "asset_type": "프린터",
    "asset_info": {
      "model_name": "Lenovo X1 3000",
      "usage": "개인",
      "serial_number": "SN-929674564"
    },
    "inspection_count": 1,
    "inspection_date": "2025-07-07T05:02:07.696Z",
    "department_confirm": "재무실",
    "is_verified": true
  },
  {
    "id": 8,
    "asset_id": 74,
    "user_id": 1,
    "inspector_name": "심규연",
    "user_team": "자동화팀",
    "asset_code": "A22487",
    "asset_type": "데스크탑",
    "asset_info": {
      "model_name": "Dell DX 700",
      "usage": "개인",
      "serial_number": "SN-869404561"
    },
    "inspection_count": 1,
    "inspection_date": "2025-07-13T00:58:56.328Z",
    "department_confirm": "재무실",
    "is_verified": true
  },
  {
    "id": 9,
    "asset_id": 58,
    "user_id": 3,
    "inspector_name": null,
    "user_team": null,
    "asset_code": "A13240",
    "asset_type": "스캐너",
    "asset_info": {
      "model_name": null,
      "usage": "개인",
      "serial_number": null
    },
    "inspection_count": 1,
    "inspection_date": "2025-07-22T19:25:16.373Z",
    "department_confirm": null,
    "is_verified": false
  },
  {
    "id": 10,
    "asset_id": 53,
    "user_id": null,
    "inspector_name": "정주혁",
    "user_team": "품질보증팀",
    "asset_code": "A53418",
    "asset_type": "데스크탑",
    "asset_info": {
      "model_name": "Apple X1 G2",
      "usage": "공용",
      "serial_number": "SN-559714391"
    },
    "inspection_count": 1,
    "inspection_date": "2025-06-23T17:30:22.937Z",
    "department_confirm": "R&D실",
    "is_verified": true
  },
  {
    "id": 11,
    "asset_id": 29,
    "user_id": 1,
    "inspector_name": null,
    "user_team": null,
    "asset_code": "A55600",
    "asset_type": "프린터",
    "asset_info": {
      "model_name": null,
      "usage": "개인",
      "serial_number": null
    },
    "inspection_count": 1,
    "inspection_date": "2025-09-08T02:55:57.351Z",
    "department_confirm": null,
    "is_verified": false
  },
  {
    "id": 12,
    "asset_id": 90,
    "user_id": 2,
    "inspector_name": null,
    "user_team": null,
    "asset_code": "A73004",
    "asset_type": "데스크탑",
    "asset_info": {
      "model_name": null,
      "usage": "개인",
      "serial_number": null
    },
    "inspection_count": 1,
    "inspection_date": "2025-08-29T13:06:13.881Z",
    "department_confirm": null,
    "is_verified": false
  },
  {
    "id": 13,
    "asset_id": 80,
    "user_id": 2,
    "inspector_name": "홍도연",
    "user_team": "자동화팀",
    "asset_code": "A34657",
    "asset_type": "모니터",
    "asset_info": {
      "model_name": "Cisco Elite 200",
      "usage": "개인",
      "serial_number": "SN-218356471"
    },
    "inspection_count": 1,
    "inspection_date": "2025-06-01T23:52:58.751Z",
    "department_confirm": "R&D실",
    "is_verified": true
  },
  {
    "id": 14,
    "asset_id": 25,
    "user_id": 2,
    "inspector_name": null,
    "user_team": null,
    "asset_code": "A05660",
    "asset_type": "노트북",
    "asset_info": {
      "model_name": null,
      "usage": "개인",
      "serial_number": null
    },
    "inspection_count": 1,
    "inspection_date": "2025-09-11T15:53:10.234Z",
    "department_confirm": null,
    "is_verified": false
  },
  {
    "id": 15,
    "asset_id": 38,
    "user_id": 1,
    "inspector_name": null,
    "user_team": null,
    "asset_code": "A98213",
    "asset_type": "데스크탑",
    "asset_info": {
      "model_name": null,
      "usage": "개인",
      "serial_number": null
    },
    "inspection_count": 1,
    "inspection_date": "2025-08-08T08:55:46.086Z",
    "department_confirm": null,
    "is_verified": false
  },
  {
    "id": 16,
    "asset_id": 87,
    "user_id": 3,
    "inspector_name": "이주주",
    "user_team": "플랫폼팀",
    "asset_code": "A02885",
    "asset_type": "데스크탑",
    "asset_info": {
      "model_name": "Mitsubishi UR M2",
      "usage": "개인",
      "serial_number": "SN-437251405"
    },
    "inspection_count": 1,
    "inspection_date": "2025-09-20T12:44:52.826Z",
    "department_confirm": "품질관리실",
    "is_verified": true
  },
  {
    "id": 17,
    "asset_id": 99,
    "user_id": 2,
    "inspector_name": "한다우",
    "user_team": "자동화팀",
    "asset_code": "A14394",
    "asset_type": "프린터",
    "asset_info": {
      "model_name": "Cisco Edge M2",
      "usage": "개인",
      "serial_number": "SN-235738123"
    },
    "inspection_count": 1,
    "inspection_date": "2025-06-01T00:49:55.716Z",
    "department_confirm": "R&D실",
    "is_verified": true
  },
  {
    "id": 18,
    "asset_id": 12,
    "user_id": 3,
    "inspector_name": "황도훈",
    "user_team": "검사팀",
    "asset_code": "A20433",
    "asset_type": "프린터",
    "asset_info": {
      "model_name": "Dell Air M2",
      "usage": "개인",
      "serial_number": "SN-390940694"
    },
    "inspection_count": 1,
    "inspection_date": "2025-06-06T21:09:49.590Z",
    "department_confirm": "품질관리실",
    "is_verified": true
  },
  {
    "id": 19,
    "asset_id": 59,
    "user_id": 2,
    "inspector_name": "서주성",
    "user_team": "품질보증팀",
    "asset_code": "A98603",
    "asset_type": "태블릿",
    "asset_info": {
      "model_name": "Samsung UR 700",
      "usage": "개인",
      "serial_number": "SN-547379194"
    },
    "inspection_count": 1,
    "inspection_date": "2025-09-13T14:39:04.038Z",
    "department_confirm": "R&D실",
    "is_verified": true
  },
  {
    "id": 20,
    "asset_id": 20,
    "user_id": 2,
    "inspector_name": "신영현",
    "user_team": "플랫폼팀",
    "asset_code": "A43230",
    "asset_type": "태블릿",
    "asset_info": {
      "model_name": "Samsung X1 900",
      "usage": "개인",
      "serial_number": "SN-338404831"
    },
    "inspection_count": 1,
    "inspection_date": "2025-06-04T15:17:46.516Z",
    "department_confirm": "R&D실",
    "is_verified": true
  },
  {
    "id": 21,
    "asset_id": 82,
    "user_id": 1,
    "inspector_name": null,
    "user_team": null,
    "asset_code": "A29390",
    "asset_type": "노트북",
    "asset_info": {
      "model_name": null,
      "usage": "개인",
      "serial_number": null
    },
    "inspection_count": 1,
    "inspection_date": "2025-08-07T15:40:48.454Z",
    "department_confirm": null,
    "is_verified": false
  },
  {
    "id": 22,
    "asset_id": 83,
    "user_id": 1,
    "inspector_name": "안지주",
    "user_team": "자동화팀",
    "asset_code": "A93870",
    "asset_type": "노트북",
    "asset_info": {
      "model_name": "Cisco Prime 10e",
      "usage": "개인",
      "serial_number": "SN-438545411"
    },
    "inspection_count": 1,
    "inspection_date": "2025-08-13T07:04:44.132Z",
    "department_confirm": "재무실",
    "is_verified": true
  },
  {
    "id": 23,
    "asset_id": 45,
    "user_id": 1,
    "inspector_name": "이예우",
    "user_team": "자동화팀",
    "asset_code": "A61820",
    "asset_type": "노트북",
    "asset_info": {
      "model_name": "Lenovo X1 200",
      "usage": "개인",
      "serial_number": "SN-410041173"
    },
    "inspection_count": 1,
    "inspection_date": "2025-08-20T14:30:00.683Z",
    "department_confirm": "재무실",
    "is_verified": true
  },
  {
    "id": 24,
    "asset_id": 41,
    "user_id": null,
    "inspector_name": "조예라",
    "user_team": "플랫폼팀",
    "asset_code": "A71317",
    "asset_type": "데스크탑",
    "asset_info": {
      "model_name": "Dell Prime G2",
      "usage": "공용",
      "serial_number": "SN-367126478"
    },
    "inspection_count": 1,
    "inspection_date": "2025-09-28T03:55:40.685Z",
    "department_confirm": "생산기술실",
    "is_verified": true
  },
  {
    "id": 25,
    "asset_id": 66,
    "user_id": null,
    "inspector_name": null,
    "user_team": null,
    "asset_code": "A82354",
    "asset_type": "노트북",
    "asset_info": {
      "model_name": null,
      "usage": "공용",
      "serial_number": null
    },
    "inspection_count": 1,
    "inspection_date": "2025-08-23T13:36:50.436Z",
    "department_confirm": null,
    "is_verified": false
  },
  {
    "id": 26,
    "asset_id": 28,
    "user_id": 2,
    "inspector_name": null,
    "user_team": null,
    "asset_code": "A12341",
    "asset_type": "프린터",
    "asset_info": {
      "model_name": null,
      "usage": "개인",
      "serial_number": null
    },
    "inspection_count": 1,
    "inspection_date": "2025-07-13T23:03:51.875Z",
    "department_confirm": null,
    "is_verified": false
  },
  {
    "id": 27,
    "asset_id": 39,
    "user_id": 3,
    "inspector_name": "송시빈",
    "user_team": "플랫폼팀",
    "asset_code": "A56236",
    "asset_type": "소모품",
    "asset_info": {
      "model_name": "Mitsubishi UR 3000",
      "usage": "개인",
      "serial_number": "SN-996308769"
    },
    "inspection_count": 1,
    "inspection_date": "2025-07-21T01:38:30.953Z",
    "department_confirm": "품질관리실",
    "is_verified": true
  },
  {
    "id": 28,
    "asset_id": 10,
    "user_id": 2,
    "inspector_name": null,
    "user_team": null,
    "asset_code": "A36828",
    "asset_type": "데스크탑",
    "asset_info": {
      "model_name": null,
      "usage": "개인",
      "serial_number": null
    },
    "inspection_count": 1,
    "inspection_date": "2025-08-29T14:00:39.550Z",
    "department_confirm": null,
    "is_verified": false
  },
  {
    "id": 29,
    "asset_id": 75,
    "user_id": 3,
    "inspector_name": "장승훈",
    "user_team": "회계팀",
    "asset_code": "A26863",
    "asset_type": "데스크탑",
    "asset_info": {
      "model_name": "LG Elite 3000",
      "usage": "개인",
      "serial_number": "SN-470518021"
    },
    "inspection_count": 1,
    "inspection_date": "2025-08-31T01:23:01.371Z",
    "department_confirm": "품질관리실",
    "is_verified": true
  },
  {
    "id": 30,
    "asset_id": 79,
    "user_id": 1,
    "inspector_name": "송하희",
    "user_team": "자동화팀",
    "asset_code": "A13623",
    "asset_type": "데스크탑",
    "asset_info": {
      "model_name": "Omron DX 100",
      "usage": "개인",
      "serial_number": "SN-853640361"
    },
    "inspection_count": 1,
    "inspection_date": "2025-07-08T11:11:52.551Z",
    "department_confirm": "재무실",
    "is_verified": true
  }
]